MANIFEST.in
README.txt
setup.py
latex2dnd/__init__.py
latex2dnd/dnd2catsoop.py
latex2dnd/dndspec.py
latex2dnd/formula.py
latex2dnd/main.py
latex2dnd.egg-info/PKG-INFO
latex2dnd.egg-info/SOURCES.txt
latex2dnd.egg-info/dependency_links.txt
latex2dnd.egg-info/entry_points.txt
latex2dnd.egg-info/requires.txt
latex2dnd.egg-info/top_level.txt
latex2dnd/lib/dnd_formulacheck.py
latex2dnd/test/__init__.py
latex2dnd/test/test_cfn.py
latex2dnd/test/test_dndspec.py
latex2dnd/test/test_errors.py
latex2dnd/test/test_examples.py
latex2dnd/test/test_gravity.py
latex2dnd/test/test_gravity2.py
latex2dnd/testtex/gravity.tex
latex2dnd/testtex/gravity2.tex
latex2dnd/testtex/gravity_bad1.tex
latex2dnd/testtex/gravity_bad2.tex
latex2dnd/testtex/gravity_bad3.tex
latex2dnd/testtex/gravity_cfn.tex
latex2dnd/testtex/gravity_simple.dndspec
latex2dnd/testtex/quadratic.tex
latex2dnd/tex/dndspec_template.tex
latex2dnd/tex/latex2dnd.tex