Metadata-Version: 2.1
Name: latex2dnd
Version: 1.2.0
Summary: Generate edX drag-and-drop problems using compilation from latex
Home-page: http://pypi.python.org/pypi/latex2dnd/
Author: I. Chuang
Author-email: ichuang@mit.edu
License: LICENSE.txt
Platform: UNKNOWN
